<PropertyList>

 <name>B1900D Pedestal</name>
 <background>Aircraft/b1900d/Panel/transparent-bg.rgb</background>
 <w>256</w>
 <h>256</h>

<instruments>


<instrument>
  <name>pedestal hotspots</name>
  <x>128</x>
  <y>128</y>
  <w>256</w>
  <h>256</h>
  <w-base>256</w-base>
  <h-base>256</h-base>

 <actions> 

   <!--             Pedestal              -->
   <action>
     <name>Toggle Autopilot</name>
     <button>0</button>
     <x>-88</x>
     <y>-14</y>
     <w>40</w>
     <h>10</h>
     <binding>
       <command>property-toggle</command>
       <property>autopilot/locks/passive-mode</property>
     </binding>
   </action>

</actions>
</instrument>
</instruments>

</PropertyList>
